target_airtable/__init__.py
target_airtable-1.3.0.dist-info/LICENSE
target_airtable-1.3.0.dist-info/METADATA
target_airtable-1.3.0.dist-info/WHEEL
target_airtable-1.3.0.dist-info/entry_points.txt
target_airtable-1.3.0.dist-info/top_level.txt
target_airtable-1.3.0.dist-info/RECORD
