Metadata-Version: 2.1
Name: target-airtable
Version: 1.3.0
Summary: Singer.io target for loading data
Home-page: https://github.com/ednarb29/target-airtable
Author: ednarb29
License: GNU Affero General Public License v3.0
Keywords: singer.io,singer-target,airtable
Platform: UNKNOWN
Classifier: Programming Language :: Python :: 3.9
Classifier: License :: OSI Approved :: GNU Affero General Public License v3
License-File: LICENSE
Requires-Dist: singer-python (>=5.0.12)
Requires-Dist: requests (>=2.27.1)
Requires-Dist: pyairtable (==1.1.0)
